setup.py
pycentosvalidators/__init__.py
pycentosvalidators/base.py
pycentosvalidators/email.py
pycentosvalidators.egg-info/PKG-INFO
pycentosvalidators.egg-info/SOURCES.txt
pycentosvalidators.egg-info/dependency_links.txt
pycentosvalidators.egg-info/not-zip-safe
pycentosvalidators.egg-info/requires.txt
pycentosvalidators.egg-info/top_level.txt