Metadata-Version: 1.0
Name: pycentosvalidators
Version: 0.0.1
Summary: Common pycentosvalidators component.
Home-page: https://github.com/istommao/pyvalidators
Author: feiger
Author-email: 351275698@qq.com
License: MIT License
Keywords: pycentosvalidators is a common validators component,only testing!
Platform: UNKNOWN
